[
  {
    "ContainingType": "Homestay.Api.Controllers.AuthController",
    "Method": "ForgotPassword",
    "RelativePath": "api/Auth/forgot-pass",
    "HttpMethod": "DELETE",
    "IsController": true,
    "Order": 0,
    "Parameters": [],
    "ReturnTypes": []
  },
  {
    "ContainingType": "Homestay.Api.Controllers.AuthController",
    "Method": "AuthLogin",
    "RelativePath": "api/Auth/login",
    "HttpMethod": "POST",
    "IsController": true,
    "Order": 0,
    "Parameters": [
      {
        "Name": "userRequest",
        "Type": "Homestay.Application.DTOS.Users.UserRequest",
        "IsRequired": true
      }
    ],
    "ReturnTypes": []
  },
  {
    "ContainingType": "Homestay.Api.Controllers.AuthController",
    "Method": "Logout",
    "RelativePath": "api/Auth/logout",
    "HttpMethod": "DELETE",
    "IsController": true,
    "Order": 0,
    "Parameters": [],
    "ReturnTypes": []
  },
  {
    "ContainingType": "Homestay.Api.Controllers.AuthController",
    "Method": "AuthRegisterAsync",
    "RelativePath": "api/Auth/register",
    "HttpMethod": "POST",
    "IsController": true,
    "Order": 0,
    "Parameters": [
      {
        "Name": "registerRequest",
        "Type": "Homestay.Application.DTOS.Users.RegisterRequest",
        "IsRequired": true
      }
    ],
    "ReturnTypes": []
  },
  {
    "ContainingType": "Homestay.Api.Controllers.AuthController",
    "Method": "AuthRegister",
    "RelativePath": "api/Auth/test",
    "HttpMethod": "POST",
    "IsController": true,
    "Order": 0,
    "Parameters": [],
    "ReturnTypes": []
  },
  {
    "ContainingType": "Homestay.Api.Controllers.RoomsController",
    "Method": "FindRoom",
    "RelativePath": "api/Rooms/roomfind",
    "HttpMethod": "GET",
    "IsController": true,
    "Order": 0,
    "Parameters": [
      {
        "Name": "DiaChi",
        "Type": "System.String",
        "IsRequired": false
      },
      {
        "Name": "MucGiaMin",
        "Type": "System.Nullable\u00601[[System.Decimal, System.Private.CoreLib, Version=8.0.0.0, Culture=neutral, PublicKeyToken=7cec85d7bea7798e]]",
        "IsRequired": false
      },
      {
        "Name": "MucGiaMax",
        "Type": "System.Nullable\u00601[[System.Decimal, System.Private.CoreLib, Version=8.0.0.0, Culture=neutral, PublicKeyToken=7cec85d7bea7798e]]",
        "IsRequired": false
      },
      {
        "Name": "SoSao",
        "Type": "System.Nullable\u00601[[System.Single, System.Private.CoreLib, Version=8.0.0.0, Culture=neutral, PublicKeyToken=7cec85d7bea7798e]]",
        "IsRequired": false
      },
      {
        "Name": "SucChua",
        "Type": "System.Nullable\u00601[[System.Int32, System.Private.CoreLib, Version=8.0.0.0, Culture=neutral, PublicKeyToken=7cec85d7bea7798e]]",
        "IsRequired": false
      }
    ],
    "ReturnTypes": []
  },
  {
    "ContainingType": "Homestay.Api.Controllers.RoomsController",
    "Method": "GetAllRoomsType",
    "RelativePath": "api/Rooms/roomtype",
    "HttpMethod": "GET",
    "IsController": true,
    "Order": 0,
    "Parameters": [
      {
        "Name": "type",
        "Type": "System.String",
        "IsRequired": false
      }
    ],
    "ReturnTypes": []
  }
]